{"playlist": {"updateTime": 1522067569376, "ordered": true, "creator": {"followed": false, "remarkName": null, "expertTags": null, "userId": 572062210, "authority": 0, "userType": 0, "experts": null, "gender": 0, "backgroundImgId": 109951163208514422, "city": 1010000, "mutual": false, "avatarUrl": "http://p1.music.126.net/kquyMtv8e2t09EWF9etf9g==/109951163208523609.jpg", "avatarImgIdStr": "109951163208523609", "detailDescription": "", "province": 1000000, "description": "", "avatarImgId_str": "109951163208523609", "birthday": -2209017600000, "nickname": "我只能撑三秒", "vipType": 0, "avatarImgId": 109951163208523609, "defaultAvatar": false, "djStatus": 0, "accountStatus": 0, "backgroundImgIdStr": "109951163208514422", "backgroundUrl": "http://p1.music.126.net/7K3Cob5R33jnsYUbwP1kNA==/109951163208514422.jpg", "signature": "这个人很懒 什么也没留下", "authStatus": 0}, "trackUpdateTime": 1522122901815, "coverImgId_str": "109951163208515253", "userId": 572062210, "coverImgUrl": "http://p1.music.126.net/wu9jc9Oe9bNyRoxGZYNJiQ==/109951163208515253.jpg", "commentCount": 0, "newImported": false, "commentThreadId": "A_PL_0_2154527293", "subscribed": false, "privacy": 0, "id": 2154527293, "trackCount": 26, "specialType": 0, "status": 0, "description": "让我告诉你\n\n我就是沙尘 空气 十二点的钟声 夜幕中坠落的飞鸟 让你窒息的汪洋 以及疯子", "subscribedCount": 320, "tags": ["后摇"], "trackNumberUpdateTime": 1522067569376, "tracks": [{"al": {"picUrl": "http://p1.music.126.net/Xj-twoyfnv75wcpg3IN8RQ==/1810895650954359.jpg", "pic": 1810895650954359, "id": 399323, "tns": [], "name": "Who You Are Is Not Enough"}, "pop": 95.0, "cd": "1", "s_id": 0, "ar": [{"alias": [], "id": 88009, "tns": [], "name": "Athletics"}], "cp": 0, "id": 3947465, "rt": "", "fee": 0, "copyright": 2, "no": 1, "rtUrl": null, "mst": 9, "rtUrls": [], "ftype": 0, "h": {"vd": -2.2, "fid": 0, "br": 320000, "size": 13019676}, "rurl": null, "publishTime": 1340640000007, "v": 7, "cf": "", "dt": 325000, "pst": 0, "a": null, "name": "I", "rtype": 0, "alia": [], "m": {"vd": -1.79, "fid": 0, "br": 160000, "size": 6517276}, "l": {"vd": -1.83, "fid": 0, "br": 96000, "size": 3915898}, "st": 0, "djId": 0, "mv": 0, "t": 0, "crbt": null}, {"al": {"picUrl": "http://p1.music.126.net/Xj-twoyfnv75wcpg3IN8RQ==/1810895650954359.jpg", "pic": 1810895650954359, "id": 399323, "tns": [], "name": "Who You Are Is Not Enough"}, "pop": 100.0, "cd": "1", "s_id": 0, "ar": [{"alias": [], "id": 88009, "tns": [], "name": "Athletics"}], "cp": 0, "id": 3947466, "rt": "", "fee": 0, "copyright": 2, "no": 2, "rtUrl": null, "mst": 9, "rtUrls": [], "ftype": 0, "h": {"vd": -1.63, "fid": 0, "br": 320000, "size": 22238812}, "rurl": null, "publishTime": 1340640000007, "v": 8, "cf": "", "dt": 555000, "pst": 0, "a": null, "name": "II", "rtype": 0, "alia": [], "m": {"vd": -1.22, "fid": 0, "br": 160000, "size": 11126846}, "l": {"vd": -1.25, "fid": 0, "br": 96000, "size": 6681641}, "st": 0, "djId": 0, "mv": 0, "t": 0, "crbt": null}, {"al": {"picUrl": "http://p1.music.126.net/Xj-twoyfnv75wcpg3IN8RQ==/1810895650954359.jpg", "pic": 1810895650954359, "id": 399323, "tns": [], "name": "Who You Are Is Not Enough"}, "pop": 100.0, "cd": "1", "s_id": 0, "ar": [{"alias": [], "id": 88009, "tns": [], "name": "Athletics"}], "cp": 0, "id": 3947467, "rt": "", "fee": 0, "copyright": 2, "no": 3, "rtUrl": null, "mst": 9, "rtUrls": [], "ftype": 0, "h": {"vd": -2.73, "fid": 0, "br": 320000, "size": 14835712}, "rurl": null, "publishTime": 1340640000007, "v": 7, "cf": "", "dt": 370000, "pst": 0, "a": null, "name": "III", "rtype": 0, "alia": [], "m": {"vd": -2.32, "fid": 0, "br": 160000, "size": 7425297}, "l": {"vd": -2.37, "fid": 0, "br": 96000, "size": 4460712}, "st": 0, "djId": 0, "mv": 0, "t": 0, "crbt": null}, {"al": {"picUrl": "http://p1.music.126.net/Xj-twoyfnv75wcpg3IN8RQ==/1810895650954359.jpg", "pic": 1810895650954359, "id": 399323, "tns": [], "name": "Who You Are Is Not Enough"}, "pop": 100.0, "cd": "1", "s_id": 0, "ar": [{"alias": [], "id": 88009, "tns": [], "name": "Athletics"}], "cp": 0, "id": 3947469, "rt": "", "fee": 0, "copyright": 2, "no": 4, "rtUrl": null, "mst": 9, "rtUrls": [], "ftype": 0, "h": {"vd": -0.72, "fid": 0, "br": 320000, "size": 14413571}, "rurl": null, "publishTime": 1340640000007, "v": 7, "cf": "", "dt": 359000, "pst": 0, "a": null, "name": "IV", "rtype": 0, "alia": [], "m": {"vd": -0.31, "fid": 0, "br": 160000, "size": 7214225}, "l": {"vd": -0.34, "fid": 0, "br": 96000, "size": 4334069}, "st": 0, "djId": 0, "mv": 0, "t": 0, "crbt": null}, {"al": {"picUrl": "http://p1.music.126.net/Xj-twoyfnv75wcpg3IN8RQ==/1810895650954359.jpg", "pic": 1810895650954359, "id": 399323, "tns": [], "name": "Who You Are Is Not Enough"}, "pop": 90.0, "cd": "1", "s_id": 0, "ar": [{"alias": [], "id": 88009, "tns": [], "name": "Athletics"}], "cp": 0, "id": 3947471, "rt": "", "fee": 0, "copyright": 2, "no": 5, "rtUrl": null, "mst": 9, "rtUrls": [], "ftype": 0, "h": {"vd": -0.000265076, "fid": 0, "br": 320000, "size": 9852590}, "rurl": null, "publishTime": 1340640000007, "v": 7, "cf": "", "dt": 245000, "pst": 0, "a": null, "name": "V", "rtype": 0, "alia": [], "m": {"vd": 0.363228, "fid": 0, "br": 160000, "size": 4933734}, "l": {"vd": -0.000265076, "fid": 0, "br": 96000, "size": 2965773}, "st": 0, "djId": 0, "mv": 0, "t": 0, "crbt": null}, {"al": {"picUrl": "http://p1.music.126.net/0e2SVhhTRrtI-wT0Jn_Bcw==/2533274790413844.jpg", "pic": 2533274790413844, "id": 3014100, "tns": [], "name": "蓿"}, "pop": 90.0, "cd": "1", "s_id": 0, "ar": [{"alias": [], "id": 11311, "tns": [], "name": "重返袖珍时光"}], "cp": 0, "id": 29371215, "rt": null, "fee": 0, "copyright": 2, "no": 0, "rtUrl": null, "mst": 9, "rtUrls": [], "ftype": 0, "h": {"vd": -0.000265076, "fid": 0, "br": 320000, "size": 20465374}, "rurl": null, "publishTime": 1254326400000, "v": 2, "cf": "", "dt": 511555, "pst": 0, "a": null, "name": "蓿", "rtype": 0, "alia": [], "m": {"vd": -0.000265076, "fid": 0, "br": 160000, "size": 10233212}, "l": {"vd": -0.000265076, "fid": 0, "br": 96000, "size": 6140347}, "st": 0, "djId": 0, "mv": 0, "t": 0, "crbt": null}, {"al": {"picUrl": "http://p1.music.126.net/1lFh18rROX8hmdLwouhlDg==/5969248627712373.jpg", "pic": 5969248627712373, "id": 2341359, "tns": [], "name": "空中狂欢节"}, "pop": 85.0, "cd": "1", "s_id": 0, "ar": [{"alias": [], "id": 12082, "tns": [], "name": "空中狂欢节"}], "cp": 0, "id": 25923409, "rt": "", "fee": 0, "copyright": 2, "no": 8, "rtUrl": null, "mst": 9, "rtUrls": [], "ftype": 0, "h": {"vd": -1.32, "fid": 0, "br": 320000, "size": 13372609}, "rurl": null, "publishTime": 1309449600007, "v": 2, "cf": "", "dt": 334000, "pst": 0, "a": null, "name": "懒阳", "rtype": 0, "alia": [], "m": {"vd": -0.89, "fid": 0, "br": 160000, "size": 6686830}, "l": {"vd": -0.96, "fid": 0, "br": 96000, "size": 4012518}, "st": 0, "djId": 0, "mv": 0, "t": 0, "crbt": null}, {"al": {"picUrl": "http://p1.music.126.net/PShUddwRw99wyJEuQSCRpA==/46179488378843.jpg", "pic": 46179488378843, "id": 10706, "tns": [], "name": "刺青 "}, "pop": 85.0, "cd": "1", "s_id": 0, "ar": [{"alias": [], "id": 3649, "tns": [], "name": "昆虫白"}], "cp": 5003, "id": 107810, "rt": "", "fee": 0, "copyright": 1, "no": 2, "rtUrl": null, "mst": 9, "rtUrls": [], "ftype": 0, "h": {"vd": -3.31, "fid": 0, "br": 192000, "size": 4207237}, "rurl": null, "publishTime": 1177603200000, "v": 3, "cf": "", "dt": 152685, "pst": 0, "a": null, "name": "旭茉莉", "rtype": 0, "alia": [], "m": {"vd": -2.9, "fid": 0, "br": 160000, "size": 3078086}, "l": {"vd": -2.95, "fid": 0, "br": 96000, "size": 1856182}, "st": 0, "djId": 0, "mv": 0, "t": 0, "crbt": null}, {"al": {"picUrl": "http://p1.music.126.net/TnE-dgbwI1qypHb9IGZcWA==/2533274791147068.jpg", "pic": 2533274791147068, "id": 3029288, "tns": [], "name": "The Last Dawn"}, "pop": 85.0, "cd": "1", "s_id": 0, "ar": [{"alias": [], "id": 20452, "tns": [], "name": "MONO"}], "cp": 663018, "id": 29460781, "rt": null, "fee": 0, "copyright": 2, "no": 2, "rtUrl": null, "mst": 9, "rtUrls": [], "ftype": 0, "h": {"vd": -1.45, "fid": 0, "br": 320000, "size": 15252388}, "rurl": null, "publishTime": 1414080000007, "v": 6, "cf": "", "dt": 381544, "pst": 0, "a": null, "name": "Katana", "rtype": 0, "alia": [], "m": {"vd": -1.02, "fid": 0, "br": 160000, "size": 7626724}, "l": {"vd": -1.03, "fid": 0, "br": 96000, "size": 4576458}, "st": 0, "djId": 0, "mv": 0, "t": 0, "crbt": null}, {"al": {"name": "Leaves", "tns": [], "pic_str": "18501482162515913", "pic": 18501482162515913, "picUrl": "http://p1.music.126.net/nLWQPj8ZFPC8uKrOKTCMfg==/18501482162515913.jpg", "id": 35561572}, "pop": 80.0, "cd": "1", "s_id": 0, "ar": [{"alias": [], "id": 145332, "tns": [], "name": "Taiko"}], "cp": 0, "id": 481535836, "rt": null, "fee": 0, "copyright": 0, "no": 1, "rtUrl": null, "mst": 9, "rtUrls": [], "ftype": 0, "h": {"vd": 0.868826, "fid": 0, "br": 320000, "size": 8762558}, "rurl": null, "publishTime": 1476028800007, "v": 3, "cf": "", "dt": 218998, "pst": 0, "a": null, "name": "Leaves", "rtype": 0, "alia": [], "m": {"vd": 1.06737, "fid": 0, "br": 160000, "size": 4381302}, "l": {"vd": 0.805192, "fid": 0, "br": 96000, "size": 2628799}, "st": 0, "djId": 0, "mv": 0, "t": 0, "crbt": null}], "highQuality": false, "subscribers": [], "playCount": 33, "coverImgId": 109951163208515253, "createTime": 1521865980790, "name": "難自渡", "trackIds": [{"id": 3947465, "v": 7}, {"id": 3947466, "v": 8}, {"id": 3947467, "v": 7}, {"id": 3947469, "v": 7}, {"id": 3947471, "v": 7}, {"id": 29371215, "v": 2}, {"id": 25923409, "v": 2}, {"id": 107810, "v": 3}, {"id": 29460781, "v": 6}, {"id": 481535836, "v": 3}, {"id": 30064172, "v": 6}, {"id": 385322, "v": 7}, {"id": 350147, "v": 16}, {"id": 28164935, "v": 4}, {"id": 356760, "v": 7}, {"id": 350113, "v": 11}, {"id": 427609266, "v": 2}, {"id": 454711600, "v": 3}, {"id": 29600656, "v": 7}, {"id": 33471965, "v": 5}, {"id": 350127, "v": 4}, {"id": 409931403, "v": 6}, {"id": 350145, "v": 18}, {"id": 350139, "v": 18}, {"id": 28853836, "v": 4}, {"id": 457212399, "v": 5}], "cloudTrackCount": 0, "shareCount": 1, "adType": 0}, "code": 200, "privileges": [{"toast": false, "dl": 0, "fee": 0, "subp": 1, "sp": 7, "preSell": false, "st": -100, "payed": 0, "flag": 0, "maxbr": 320000, "cs": false, "cp": 1, "fl": 320000, "id": 3947465, "pl": 0}, {"toast": false, "dl": 0, "fee": 0, "subp": 1, "sp": 7, "preSell": false, "st": -100, "payed": 0, "flag": 0, "maxbr": 320000, "cs": false, "cp": 1, "fl": 320000, "id": 3947466, "pl": 0}, {"toast": false, "dl": 0, "fee": 0, "subp": 1, "sp": 7, "preSell": false, "st": -100, "payed": 0, "flag": 0, "maxbr": 320000, "cs": false, "cp": 1, "fl": 320000, "id": 3947467, "pl": 0}, {"toast": false, "dl": 0, "fee": 0, "subp": 1, "sp": 7, "preSell": false, "st": -100, "payed": 0, "flag": 0, "maxbr": 320000, "cs": false, "cp": 1, "fl": 320000, "id": 3947469, "pl": 0}, {"toast": false, "dl": 0, "fee": 0, "subp": 1, "sp": 7, "preSell": false, "st": -100, "payed": 0, "flag": 0, "maxbr": 320000, "cs": false, "cp": 1, "fl": 320000, "id": 3947471, "pl": 0}, {"toast": false, "dl": 0, "fee": 0, "subp": 1, "sp": 7, "preSell": false, "st": -100, "payed": 0, "flag": 0, "maxbr": 320000, "cs": false, "cp": 1, "fl": 320000, "id": 29371215, "pl": 0}, {"toast": false, "dl": 0, "fee": 0, "subp": 1, "sp": 7, "preSell": false, "st": -100, "payed": 0, "flag": 0, "maxbr": 320000, "cs": false, "cp": 1, "fl": 320000, "id": 25923409, "pl": 0}, {"toast": false, "dl": 0, "fee": 0, "subp": 1, "sp": 7, "preSell": false, "st": -100, "payed": 0, "flag": 0, "maxbr": 192000, "cs": false, "cp": 1, "fl": 0, "id": 107810, "pl": 0}, {"toast": false, "dl": 0, "fee": 0, "subp": 1, "sp": 7, "preSell": false, "st": -100, "payed": 0, "flag": 0, "maxbr": 320000, "cs": false, "cp": 1, "fl": 320000, "id": 29460781, "pl": 0}, {"toast": false, "dl": 0, "fee": 0, "subp": 1, "sp": 7, "preSell": false, "st": -100, "payed": 0, "flag": 0, "maxbr": 320000, "cs": false, "cp": 1, "fl": 320000, "id": 481535836, "pl": 0}]}