{"playlist": {"updateTime": 1522057989789, "ordered": true, "creator": {"followed": false, "remarkName": null, "expertTags": null, "userId": 1375076520, "authority": 0, "userType": 0, "experts": null, "gender": 2, "backgroundImgId": 109951163193716359, "city": 440300, "mutual": false, "avatarUrl": "http://p1.music.126.net/50aOTPIk6MYiA04esXL9_w==/109951163196459460.jpg", "avatarImgIdStr": "109951163196459460", "detailDescription": "", "province": 440000, "description": "", "avatarImgId_str": "109951163196459460", "birthday": -2209017600000, "nickname": "Danyka", "vipType": 0, "avatarImgId": 109951163196459460, "defaultAvatar": false, "djStatus": 0, "accountStatus": 0, "backgroundImgIdStr": "109951163193716359", "backgroundUrl": "http://p1.music.126.net/2mUs2fH7hHLr4avcu83uhg==/109951163193716359.jpg", "signature": "-", "authStatus": 0}, "trackUpdateTime": 1522058927109, "coverImgId_str": "18984167765763419", "userId": 1375076520, "coverImgUrl": "http://p1.music.126.net/7PGNnF72efCw0xsq0PsTLQ==/18984167765763419.jpg", "commentCount": 559, "newImported": false, "commentThreadId": "A_PL_0_2109339318", "subscribed": false, "privacy": 0, "id": 2109339318, "trackCount": 33, "specialType": 0, "status": 0, "description": "可爱的小姐姐们进来啦~\n\n介绍一下噢，选曲都是男声，冷门热门都有。\n\n做这个歌单是在听一首情歌时萌生出来的:我想和唱这歌的小哥哥谈恋爱\n(脸红/// v///)\n肯定不止我一个啊喂\n\n然后就产生了这个歌单噜\n\n人生不来场和小哥哥的恋爱怎么能圆满呢 ///v///\n\n—————————————————————————————\n\nend-Danyka", "subscribedCount": 37286, "tags": ["欧美", "流行", "电子"], "coverImgId": 18984167765763419, "tracks": [{"al": {"name": "Hard to Love You (Final 28 Mix)", "tns": [], "pic_str": "109951163192289847", "pic": 109951163192289847, "picUrl": "http://p1.music.126.net/LRAkaKJXuZN0CaipcGEu3w==/109951163192289847.jpg", "id": 37767737}, "pop": 20.0, "cd": "1", "s_id": 0, "ar": [{"alias": [], "id": 12335065, "tns": [], "name": "Marco Cavax"}], "cp": 7001, "id": 545655918, "rt": null, "fee": 8, "copyright": 1, "no": 1, "rtUrl": null, "mst": 9, "rtUrls": [], "ftype": 0, "h": {"vd": -1.0, "fid": 0, "br": 320000, "size": 6823227}, "rurl": null, "publishTime": 1521734400007, "v": 1, "cf": "", "dt": 170553, "pst": 0, "a": null, "name": "Hard to Love You (Final 28 Mix)", "rtype": 0, "alia": [], "m": {"vd": -1.0, "fid": 0, "br": 192000, "size": 4093954}, "l": {"vd": -1.0, "fid": 0, "br": 128000, "size": 2729317}, "st": 0, "djId": 0, "mv": 0, "t": 0, "crbt": null}, {"al": {"name": "LøVë", "tns": [], "pic_str": "18578447976246937", "pic": 18578447976246937, "picUrl": "http://p1.music.126.net/4Nl_TS3zZTVWaLg0-PhCow==/18578447976246937.jpg", "id": 35139087}, "pop": 100.0, "cd": "1", "s_id": 0, "ar": [{"alias": [], "id": 27598, "tns": [], "name": "Aaron Carter"}], "cp": 7001, "id": 454730079, "rt": null, "fee": 8, "copyright": 2, "no": 3, "rtUrl": null, "mst": 9, "rtUrls": [], "ftype": 0, "h": {"vd": -0.87, "fid": 0, "br": 320000, "size": 8505513}, "rurl": null, "publishTime": 1486656000007, "v": 32, "cf": "", "dt": 212564, "pst": 0, "a": null, "name": "Sooner Or Later", "rtype": 0, "alia": [], "m": {"vd": -0.46, "fid": 0, "br": 160000, "size": 4252779}, "l": {"vd": -0.56, "fid": 0, "br": 96000, "size": 2551685}, "st": 0, "djId": 0, "mv": 5594069, "t": 0, "crbt": null}, {"al": {"name": "If U Wanted To", "tns": [], "pic_str": "109951163160872636", "pic": 109951163160872636, "picUrl": "http://p1.music.126.net/Imxvy6RIDu6vEDRa9oFqLw==/109951163160872636.jpg", "id": 37590823}, "pop": 90.0, "cd": "1", "s_id": 0, "ar": [{"alias": [], "id": 952248, "tns": [], "name": "Fabian Mazur"}, {"alias": [], "id": 30796, "tns": [], "name": "Cameron Forbes"}], "cp": 631010, "id": 539982704, "rt": null, "fee": 8, "copyright": 1, "no": 1, "rtUrl": null, "mst": 9, "rtUrls": [], "ftype": 0, "h": {"vd": -2.0, "fid": 0, "br": 320000, "size": 9198280}, "rurl": null, "publishTime": 1520524800007, "v": 1, "cf": "", "dt": 229890, "pst": 0, "a": null, "name": "If U Wanted To", "rtype": 0, "alia": [], "m": {"vd": -1.0, "fid": 0, "br": 192000, "size": 5518986}, "l": {"vd": -1.0, "fid": 0, "br": 128000, "size": 3679338}, "st": 0, "djId": 0, "mv": 0, "t": 0, "crbt": null}, {"al": {"name": "What I Know", "tns": [], "pic_str": "18590542604305420", "pic": 18590542604305420, "picUrl": "http://p1.music.126.net/JCTJMMctiJC1c-cl--POGw==/18590542604305420.jpg", "id": 35297259}, "pop": 100.0, "cd": "1", "s_id": 0, "ar": [{"alias": [], "id": 996655, "tns": [], "name": "Isaac Sakima"}, {"alias": [], "id": 1057269, "tns": [], "name": "AObeats"}], "cp": 0, "id": 467805456, "rt": null, "fee": 0, "copyright": 2, "no": 1, "rtUrl": null, "mst": 9, "rtUrls": [], "ftype": 0, "h": {"vd": -1.95, "fid": 0, "br": 320000, "size": 7395831}, "rurl": null, "publishTime": 1490284800007, "v": 3, "cf": "", "dt": 184877, "pst": 0, "a": null, "name": "What I Know", "rtype": 0, "alia": [], "m": {"vd": -1.51, "fid": 0, "br": 160000, "size": 3697938}, "l": {"vd": -1.55, "fid": 0, "br": 96000, "size": 2218781}, "st": 0, "djId": 0, "mv": 0, "t": 0, "crbt": null}, {"al": {"name": "Burn", "tns": [], "pic_str": "18364043207910906", "pic": 18364043207910906, "picUrl": "http://p1.music.126.net/xhzqPNqCKoZqyoTbq4ZJzw==/18364043207910906.jpg", "id": 36685017}, "pop": 100.0, "cd": "1", "s_id": 0, "ar": [{"alias": [], "id": 1005048, "tns": [], "name": "Marnik"}, {"alias": [], "id": 12074184, "tns": [], "name": "ROOKIES"}], "cp": 7003, "id": 515627032, "rt": null, "fee": 8, "copyright": 1, "no": 1, "rtUrl": null, "mst": 9, "rtUrls": [], "ftype": 0, "h": {"vd": -2.0, "fid": 0, "br": 320000, "size": 7752142}, "rurl": null, "publishTime": 1509033600007, "v": 9, "cf": "", "dt": 193776, "pst": 0, "a": null, "name": "Burn", "rtype": 0, "alia": [], "m": {"vd": -2.0, "fid": 0, "br": 192000, "size": 4651302}, "l": {"vd": -1.0, "fid": 0, "br": 128000, "size": 3100883}, "st": 0, "djId": 0, "mv": 5794114, "t": 0, "crbt": null}, {"al": {"name": "Don't Call", "tns": [], "pic_str": "18421217812025528", "pic": 18421217812025528, "picUrl": "http://p1.music.126.net/El1wFKu00Py4QPtsO6HGpA==/18421217812025528.jpg", "id": 36901158}, "pop": 100.0, "cd": "1", "s_id": 0, "ar": [{"alias": [], "id": 847225, "tns": [], "name": "Lost Kings"}], "cp": 7001, "id": 522444290, "rt": null, "fee": 8, "copyright": 1, "no": 1, "rtUrl": null, "mst": 9, "rtUrls": [], "ftype": 0, "h": {"vd": 0.0, "fid": 0, "br": 320000, "size": 7859766}, "rurl": null, "publishTime": 1512662400007, "v": 8, "cf": "", "dt": 196466, "pst": 0, "a": null, "name": "Don't Call", "rtype": 0, "alia": [], "m": {"vd": 0.0, "fid": 0, "br": 192000, "size": 4715877}, "l": {"vd": 0.0, "fid": 0, "br": 128000, "size": 3143933}, "st": 0, "djId": 0, "mv": 5783022, "t": 0, "crbt": null}, {"al": {"name": "Pretty Stranger", "tns": [], "pic_str": "18855524904836399", "pic": 18855524904836399, "picUrl": "http://p1.music.126.net/WLklIYMI1ZlPlxIguYlUjg==/18855524904836399.jpg", "id": 36770136}, "pop": 100.0, "cd": "1", "s_id": 0, "ar": [{"alias": [], "id": 1086041, "tns": [], "name": "Prismo"}], "cp": 7002, "id": 517918245, "rt": null, "fee": 8, "copyright": 1, "no": 1, "rtUrl": null, "mst": 9, "rtUrls": [], "ftype": 0, "h": {"vd": 0.0, "fid": 0, "br": 320000, "size": 8289219}, "rurl": null, "publishTime": 1510243200007, "v": 6, "cf": "", "dt": 207203, "pst": 0, "a": null, "name": "Pretty Stranger", "rtype": 0, "alia": [], "m": {"vd": 0.0, "fid": 0, "br": 192000, "size": 4973549}, "l": {"vd": 0.0, "fid": 0, "br": 128000, "size": 3315714}, "st": 0, "djId": 0, "mv": 0, "t": 0, "crbt": null}, {"al": {"name": "cybersex", "tns": [], "pic_str": "17887954672552295", "pic": 17887954672552295, "picUrl": "http://p1.music.126.net/BT-sj_fIjcdqOsnDAvUF8Q==/17887954672552295.jpg", "id": 36861029}, "pop": 100.0, "cd": "1", "s_id": 0, "ar": [{"alias": [], "id": 1060215, "tns": [], "name": "blackbear"}, {"alias": [], "id": 12107565, "tns": [], "name": "FRND"}], "cp": 7003, "id": 520556369, "rt": null, "fee": 8, "copyright": 1, "no": 6, "rtUrl": null, "mst": 9, "rtUrls": [], "ftype": 0, "h": {"vd": -1.0, "fid": 0, "br": 320000, "size": 7644517}, "rurl": null, "publishTime": 1511452800007, "v": 19, "cf": "", "dt": 191085, "pst": 0, "a": null, "name": "anxiety", "rtype": 0, "alia": [], "m": {"vd": -1.0, "fid": 0, "br": 192000, "size": 4586728}, "l": {"vd": -1.0, "fid": 0, "br": 128000, "size": 3057833}, "st": 0, "djId": 0, "mv": 5802014, "t": 0, "crbt": null}, {"al": {"name": "Bedre End Din Ex", "tns": [], "pic_str": "17908845393485221", "pic": 17908845393485221, "picUrl": "http://p1.music.126.net/XEMfILq2pZRS5uLViEq_Qw==/17908845393485221.jpg", "id": 35770221}, "pop": 100.0, "cd": "1", "s_id": 0, "ar": [{"alias": [], "id": 1081659, "tns": [], "name": "Page Four"}], "cp": 7001, "id": 491237272, "rt": null, "fee": 8, "copyright": 1, "no": 1, "rtUrl": null, "mst": 9, "rtUrls": [], "ftype": 0, "h": {"vd": -1.0, "fid": 0, "br": 320000, "size": 8315342}, "rurl": null, "publishTime": 1499961600007, "v": 8, "cf": "", "dt": 207882, "pst": 0, "a": null, "name": "Bedre End Din Ex", "rtype": 0, "alia": [], "m": {"vd": -1.0, "fid": 0, "br": 192000, "size": 4989222}, "l": {"vd": -1.0, "fid": 0, "br": 128000, "size": 3326163}, "st": 0, "djId": 0, "mv": 0, "t": 0, "crbt": null}, {"al": {"name": "I Want You", "tns": [], "pic_str": "18930291695640602", "pic": 18930291695640602, "picUrl": "http://p1.music.126.net/8vZqHMaSGHfWKUXtnVGi5A==/18930291695640602.jpg", "id": 35695643}, "pop": 100.0, "cd": "", "s_id": 0, "ar": [{"alias": [], "id": 826205, "tns": [], "name": "Robotaki"}, {"alias": [], "id": 1147176, "tns": [], "name": "Manila Killa"}, {"alias": [], "id": 0, "tns": [], "name": "Matthew John Kurz"}], "cp": 0, "id": 488647432, "rt": null, "fee": 0, "copyright": 0, "no": 1, "rtUrl": null, "mst": 9, "rtUrls": [], "ftype": 0, "h": {"vd": -3.0, "fid": 0, "br": 320000, "size": 7380158}, "rurl": null, "publishTime": 1498665600007, "v": 5, "cf": "", "dt": 184476, "pst": 0, "a": null, "name": "I Want You", "rtype": 0, "alia": [], "m": {"vd": -3.0, "fid": 0, "br": 192000, "size": 4428112}, "l": {"vd": -3.0, "fid": 0, "br": 128000, "size": 2952089}, "st": 0, "djId": 0, "mv": 0, "t": 0, "crbt": null}], "highQuality": false, "subscribers": [], "playCount": 1358765, "trackNumberUpdateTime": 1522057989789, "createTime": 1519070117313, "name": "想和这些唱情歌的小哥哥谈场恋爱呀", "trackIds": [{"id": 545655918, "v": 1}, {"id": 454730079, "v": 32}, {"id": 539982704, "v": 1}, {"id": 467805456, "v": 3}, {"id": 515627032, "v": 9}, {"id": 522444290, "v": 8}, {"id": 517918245, "v": 6}, {"id": 520556369, "v": 19}, {"id": 491237272, "v": 8}, {"id": 488647432, "v": 5}, {"id": 526099038, "v": 15}, {"id": 526470122, "v": 4}, {"id": 515796302, "v": 5}, {"id": 526093067, "v": 4}, {"id": 500410103, "v": 6}, {"id": 533471297, "v": 4}, {"id": 526081081, "v": 24}, {"id": 466343950, "v": 13}, {"id": 479325985, "v": 2}, {"id": 414523833, "v": 2}, {"id": 533471295, "v": 4}, {"id": 29715668, "v": 7}, {"id": 529823909, "v": 18}, {"id": 489998997, "v": 6}, {"id": 487154022, "v": 5}, {"id": 492093004, "v": 9}, {"id": 529834567, "v": 7}, {"id": 534931959, "v": 8}, {"id": 459733844, "v": 2}, {"id": 515452368, "v": 4}, {"id": 529824113, "v": 5}, {"id": 500686106, "v": 15}, {"id": 411314115, "v": 2}], "cloudTrackCount": 0, "shareCount": 278, "adType": 0}, "code": 200, "privileges": [{"toast": false, "dl": 0, "fee": 0, "subp": 1, "sp": 7, "preSell": false, "st": -100, "payed": 0, "flag": 0, "maxbr": 320000, "cs": false, "cp": 1, "fl": 0, "id": 545655918, "pl": 0}, {"toast": false, "dl": 0, "fee": 0, "subp": 1, "sp": 7, "preSell": false, "st": -100, "payed": 0, "flag": 0, "maxbr": 999000, "cs": false, "cp": 1, "fl": 0, "id": 454730079, "pl": 0}, {"toast": false, "dl": 0, "fee": 0, "subp": 1, "sp": 7, "preSell": false, "st": -100, "payed": 0, "flag": 0, "maxbr": 999000, "cs": false, "cp": 1, "fl": 0, "id": 539982704, "pl": 0}, {"toast": false, "dl": 0, "fee": 0, "subp": 1, "sp": 7, "preSell": false, "st": -100, "payed": 0, "flag": 0, "maxbr": 320000, "cs": false, "cp": 1, "fl": 320000, "id": 467805456, "pl": 0}, {"toast": false, "dl": 0, "fee": 0, "subp": 1, "sp": 7, "preSell": false, "st": -100, "payed": 0, "flag": 0, "maxbr": 320000, "cs": false, "cp": 1, "fl": 0, "id": 515627032, "pl": 0}, {"toast": false, "dl": 0, "fee": 0, "subp": 1, "sp": 7, "preSell": false, "st": -100, "payed": 0, "flag": 0, "maxbr": 320000, "cs": false, "cp": 1, "fl": 0, "id": 522444290, "pl": 0}, {"toast": false, "dl": 0, "fee": 0, "subp": 1, "sp": 7, "preSell": false, "st": -100, "payed": 0, "flag": 0, "maxbr": 320000, "cs": false, "cp": 1, "fl": 0, "id": 517918245, "pl": 0}, {"toast": false, "dl": 0, "fee": 0, "subp": 1, "sp": 7, "preSell": false, "st": -100, "payed": 0, "flag": 0, "maxbr": 320000, "cs": false, "cp": 1, "fl": 0, "id": 520556369, "pl": 0}, {"toast": false, "dl": 0, "fee": 0, "subp": 1, "sp": 7, "preSell": false, "st": -100, "payed": 0, "flag": 0, "maxbr": 320000, "cs": false, "cp": 1, "fl": 0, "id": 491237272, "pl": 0}, {"toast": false, "dl": 0, "fee": 0, "subp": 1, "sp": 7, "preSell": false, "st": -100, "payed": 0, "flag": 0, "maxbr": 320000, "cs": false, "cp": 1, "fl": 320000, "id": 488647432, "pl": 0}]}