{"playlist": {"coverImgUrl": "http://p1.music.126.net/R9fW-3EZyEpz6__x3z7DDQ==/18789554209097935.jpg", "ordered": true, "creator": {"followed": false, "remarkName": null, "expertTags": ["另类/独立", "韩语"], "userId": 45803217, "authority": 0, "userType": 0, "experts": null, "gender": 2, "backgroundImgId": 109951163164830074, "city": 310101, "mutual": false, "avatarUrl": "http://p1.music.126.net/MCGM5iw6qWAk9jYtguHMCw==/109951163204631568.jpg", "avatarImgIdStr": "109951163204631568", "detailDescription": "", "province": 310000, "description": "", "avatarImgId_str": "109951163204631568", "birthday": 803664000000, "nickname": "双皮奶吃人", "vipType": 10, "avatarImgId": 109951163204631568, "defaultAvatar": false, "djStatus": 10, "accountStatus": 0, "backgroundImgIdStr": "109951163164830074", "backgroundUrl": "http://p1.music.126.net/Jo2Eios5WLH1F2svWPkeow==/109951163164830074.jpg", "signature": "原ID@Spncr_", "authStatus": 0}, "trackUpdateTime": 1519629521774, "coverImgId_str": "18789554209097935", "userId": 45803217, "updateTime": 1519621133810, "commentCount": 3, "newImported": false, "commentThreadId": "A_PL_0_908594231", "subscribed": false, "privacy": 0, "id": 908594231, "trackCount": 29, "specialType": 0, "status": 0, "description": "听够了小清新？让我们来听听节奏强劲的、Hook超中毒的电子舞曲吧！\n为何歌曲中要留白？当然是为了让你上瘾抖腿用的呀！\n\n封面：Suzy裴秀智", "subscribedCount": 229, "tags": ["韩语", "电子", "另类/独立"], "trackNumberUpdateTime": 1519518347177, "tracks": [{"al": {"name": "Drive Together", "tns": [], "pic_str": "109951163028351900", "pic": 109951163028351900, "picUrl": "http://p1.music.126.net/0wa9a7MfRJ0xw4AfPak8Dw==/109951163028351900.jpg", "id": 36225349}, "pop": 50.0, "cd": "", "s_id": 0, "ar": [{"alias": [], "id": 12645466, "tns": [], "name": "SUL"}, {"alias": [], "id": 861772, "tns": [], "name": "Microdot"}], "cp": 422010, "id": 507532080, "rt": null, "fee": 8, "copyright": 0, "no": 1, "rtUrl": null, "mst": 9, "rtUrls": [], "ftype": 0, "h": {"vd": -3.0, "fid": 0, "br": 320000, "size": 7362395}, "rurl": null, "publishTime": 1505750400007, "v": 6, "cf": "", "dt": 183848, "pst": 0, "a": null, "name": "Drive Together(Prod. YELLA D)", "rtype": 0, "alia": [], "m": {"vd": -3.0, "fid": 0, "br": 192000, "size": 4417454}, "l": {"vd": -3.0, "fid": 0, "br": 128000, "size": 2944984}, "st": 0, "djId": 0, "mv": 0, "t": 0, "crbt": null}, {"al": {"name": "Do You Love Me", "tns": [], "pic_str": "109951163029396442", "pic": 109951163029396442, "picUrl": "http://p1.music.126.net/39jKHYH7L9uDL-nPjBexNw==/109951163029396442.jpg", "id": 36303163}, "pop": 15.0, "cd": "", "s_id": 0, "ar": [{"alias": [], "id": 12274440, "tns": [], "name": "Edmmer"}, {"alias": [], "id": 1081575, "tns": [], "name": "비버"}, {"alias": [], "id": 15696, "tns": [], "name": "Terry"}], "cp": 422010, "id": 507795601, "rt": null, "fee": 8, "copyright": 0, "no": 1, "rtUrl": null, "mst": 9, "rtUrls": [], "ftype": 0, "h": {"vd": -4.0, "fid": 0, "br": 320000, "size": 9118868}, "rurl": null, "publishTime": 1506009600007, "v": 6, "cf": "", "dt": 227902, "pst": 0, "a": null, "name": "Do You Love Me?", "rtype": 0, "alia": [], "m": {"vd": -3.0, "fid": 0, "br": 192000, "size": 5471338}, "l": {"vd": -3.0, "fid": 0, "br": 128000, "size": 3647573}, "st": 0, "djId": 0, "mv": 0, "t": 0, "crbt": null}, {"al": {"name": "Story", "tns": [], "pic_str": "18864320997849195", "pic": 18864320997849195, "picUrl": "http://p1.music.126.net/LZtTwV7pK8t3HWXb4p8KXQ==/18864320997849195.jpg", "id": 35424186}, "pop": 50.0, "cd": "1", "s_id": 0, "ar": [{"alias": [], "id": 12387126, "tns": [], "name": "Minimonster"}], "cp": 0, "id": 473940307, "rt": null, "fee": 0, "copyright": 0, "no": 3, "rtUrl": null, "mst": 9, "rtUrls": [], "ftype": 0, "h": {"vd": -3.71, "fid": 0, "br": 320000, "size": 8450133}, "rurl": null, "publishTime": 1480003200007, "v": 4, "cf": "", "dt": 211200, "pst": 0, "a": null, "name": "Make It Beautiful", "rtype": 0, "alia": [], "m": {"vd": -3.27, "fid": 0, "br": 160000, "size": 4225089}, "l": {"vd": -3.3, "fid": 0, "br": 96000, "size": 2535071}, "st": 0, "djId": 0, "mv": 0, "t": 0, "crbt": null}, {"al": {"name": "Baking Soda", "tns": [], "pic_str": "19071029184023335", "pic": 19071029184023335, "picUrl": "http://p1.music.126.net/YQflwGBGR3DGZ4KC-k5XZg==/19071029184023335.jpg", "id": 35792381}, "pop": 25.0, "cd": "", "s_id": 0, "ar": [{"alias": [], "id": 12523518, "tns": [], "name": "TAM TAM"}, {"alias": [], "id": 0, "tns": [], "name": "Peppe"}], "cp": 0, "id": 491955309, "rt": null, "fee": 0, "copyright": 0, "no": 1, "rtUrl": null, "mst": 9, "rtUrls": [], "ftype": 0, "h": {"vd": -5.0, "fid": 0, "br": 320000, "size": 8152338}, "rurl": null, "publishTime": 1500393600007, "v": 4, "cf": "", "dt": 203781, "pst": 0, "a": null, "name": "Baking Soda", "rtype": 0, "alia": [], "m": {"vd": -4.0, "fid": 0, "br": 192000, "size": 4891420}, "l": {"vd": -4.0, "fid": 0, "br": 128000, "size": 3260961}, "st": 0, "djId": 0, "mv": 0, "t": 0, "crbt": null}, {"al": {"name": "Rainbow", "tns": [], "pic_str": "17908845393479666", "pic": 17908845393479666, "picUrl": "http://p1.music.126.net/jZuzm1nA8-JyDKHPW7C1uw==/17908845393479666.jpg", "id": 35454522}, "pop": 25.0, "cd": "1", "s_id": 0, "ar": [{"alias": [], "id": 11999076, "tns": [], "name": "DJ IT"}, {"alias": [], "id": 12143078, "tns": [], "name": "Aisle"}], "cp": 7002, "id": 476569154, "rt": null, "fee": 8, "copyright": 1, "no": 1, "rtUrl": null, "mst": 9, "rtUrls": [], "ftype": 0, "h": {"vd": -3.24, "fid": 0, "br": 320000, "size": 8574476}, "rurl": null, "publishTime": 1493395200007, "v": 2, "cf": "", "dt": 214334, "pst": 0, "a": null, "name": "Rainbow", "rtype": 0, "alia": [], "m": {"vd": -2.79, "fid": 0, "br": 160000, "size": 4287261}, "l": {"vd": -2.85, "fid": 0, "br": 96000, "size": 2572374}, "st": 0, "djId": 0, "mv": 0, "t": 0, "crbt": null}, {"al": {"name": "Monster", "tns": [], "pic_str": "18288176905327140", "pic": 18288176905327140, "picUrl": "http://p1.music.126.net/Q1HHdQqTgPzxXjqRCizuEQ==/18288176905327140.jpg", "id": 35349303}, "pop": 20.0, "cd": "1", "s_id": 0, "ar": [{"alias": [], "id": 12108004, "tns": [], "name": "PALGOU"}], "cp": 7002, "id": 470670960, "rt": null, "fee": 8, "copyright": 1, "no": 1, "rtUrl": null, "mst": 9, "rtUrls": [], "ftype": 0, "h": {"vd": -3.16, "fid": 0, "br": 320000, "size": 10561872}, "rurl": null, "publishTime": 1491321600007, "v": 2, "cf": "", "dt": 264019, "pst": 0, "a": null, "name": "Monster", "rtype": 0, "alia": [], "m": {"vd": -2.76, "fid": 0, "br": 160000, "size": 5280959}, "l": {"vd": -2.83, "fid": 0, "br": 96000, "size": 3168593}, "st": 0, "djId": 0, "mv": 0, "t": 0, "crbt": null}, {"al": {"name": "WAY", "tns": [], "pic_str": "17827481533182473", "pic": 17827481533182473, "picUrl": "http://p1.music.126.net/oT7VvX1vvxzWCNFDfEDJyA==/17827481533182473.jpg", "id": 35757184}, "pop": 70.0, "cd": "1", "s_id": 0, "ar": [{"alias": [], "id": 12196150, "tns": [], "name": "서노찌"}, {"alias": [], "id": 0, "tns": [], "name": "이미쉘"}], "cp": 7002, "id": 490602605, "rt": null, "fee": 8, "copyright": 0, "no": 1, "rtUrl": null, "mst": 9, "rtUrls": [], "ftype": 0, "h": {"vd": -2.0, "fid": 0, "br": 320000, "size": 8619407}, "rurl": null, "publishTime": 1500134400007, "v": 6, "cf": "", "dt": 215457, "pst": 0, "a": null, "name": "WAY", "rtype": 0, "alia": [], "m": {"vd": -2.0, "fid": 0, "br": 192000, "size": 5171662}, "l": {"vd": -2.0, "fid": 0, "br": 128000, "size": 3447789}, "st": 0, "djId": 0, "mv": 0, "t": 0, "crbt": null}, {"al": {"name": "Parade (Besukih winter palace remix)", "tns": [], "pic_str": "17819784951788957", "pic": 17819784951788957, "picUrl": "http://p1.music.126.net/GhchzCKgFXApHrP0ckRc1Q==/17819784951788957.jpg", "id": 35947876}, "pop": 5.0, "cd": "1", "s_id": 0, "ar": [{"alias": [], "id": 1156427, "tns": [], "name": "Floating Island"}], "cp": 422010, "id": 498393830, "rt": null, "fee": 8, "copyright": 1, "no": 1, "rtUrl": null, "mst": 9, "rtUrls": [], "ftype": 0, "h": {"vd": 0.0, "fid": 0, "br": 320000, "size": 11882623}, "rurl": null, "publishTime": 1471363200007, "v": 4, "cf": "", "dt": 297012, "pst": 0, "a": null, "name": "Parade (Besukih winter palace remix)", "rtype": 0, "alia": [], "m": {"vd": 0.0, "fid": 0, "br": 192000, "size": 7129591}, "l": {"vd": 0.0, "fid": 0, "br": 128000, "size": 4753075}, "st": 0, "djId": 0, "mv": 0, "t": 0, "crbt": null}, {"al": {"name": "LOVE GENERATION", "tns": [], "pic_str": "109951163008477227", "pic": 109951163008477227, "picUrl": "http://p1.music.126.net/Xp3bEu4jZJ8g2nji_NtLUA==/109951163008477227.jpg", "id": 36030014}, "pop": 60.0, "cd": "", "s_id": 0, "ar": [{"alias": [], "id": 1144034, "tns": [], "name": "DIA"}], "cp": 0, "id": 500686039, "rt": null, "fee": 0, "copyright": 0, "no": 11, "rtUrl": null, "mst": 9, "rtUrls": [], "ftype": 0, "h": {"vd": -3.0, "fid": 0, "br": 320000, "size": 8942280}, "rurl": null, "publishTime": 1503331200007, "v": 5, "cf": "", "dt": 223503, "pst": 0, "a": null, "name": "파라다이스 (Limited Ver.)", "tns": ["Paradise"], "rtype": 0, "alia": [], "m": {"vd": -2.0, "fid": 0, "br": 192000, "size": 5365386}, "l": {"vd": -2.0, "fid": 0, "br": 128000, "size": 3576938}, "st": 0, "djId": 0, "mv": 0, "t": 0, "crbt": null}, {"al": {"name": "Draw And Fill", "tns": [], "pic_str": "109951163028886026", "pic": 109951163028886026, "picUrl": "http://p1.music.126.net/GEPU7_HMoQ6lO6uCQFzcpQ==/109951163028886026.jpg", "id": 36303047}, "pop": 25.0, "cd": "", "s_id": 0, "ar": [{"alias": [], "id": 12646081, "tns": [], "name": "HWAJA"}], "cp": 422010, "id": 507795110, "rt": null, "fee": 8, "copyright": 0, "no": 1, "rtUrl": null, "mst": 9, "rtUrls": [], "ftype": 0, "h": {"vd": -3.0, "fid": 0, "br": 320000, "size": 8013366}, "rurl": null, "publishTime": 1505923200007, "v": 6, "cf": "", "dt": 200278, "pst": 0, "a": null, "name": "그려 (draw)", "rtype": 0, "alia": [], "m": {"vd": -2.0, "fid": 0, "br": 192000, "size": 4808037}, "l": {"vd": -2.0, "fid": 0, "br": 128000, "size": 3205373}, "st": 0, "djId": 0, "mv": 0, "t": 0, "crbt": null}], "highQuality": false, "subscribers": [], "playCount": 27080, "coverImgId": 18789554209097935, "createTime": 1504663199642, "name": "留白之美♫ 刺激神经的魔怔HOOK", "trackIds": [{"id": 507532080, "v": 6}, {"id": 507795601, "v": 6}, {"id": 473940307, "v": 4}, {"id": 491955309, "v": 4}, {"id": 476569154, "v": 2}, {"id": 470670960, "v": 2}, {"id": 490602605, "v": 6}, {"id": 498393830, "v": 4}, {"id": 500686039, "v": 5}, {"id": 507795110, "v": 6}, {"id": 531051013, "v": 6}, {"id": 488256862, "v": 10}, {"id": 465973317, "v": 6}, {"id": 485612315, "v": 7}, {"id": 507795111, "v": 4}, {"id": 507783891, "v": 4}, {"id": 488267361, "v": 4}, {"id": 498286437, "v": 6}, {"id": 35617452, "v": 7}, {"id": 473817880, "v": 4}, {"id": 491950422, "v": 4}, {"id": 489770257, "v": 6}, {"id": 503268151, "v": 7}, {"id": 484058237, "v": 5}, {"id": 494645738, "v": 6}, {"id": 450222522, "v": 4}, {"id": 460043303, "v": 4}, {"id": 479028052, "v": 5}, {"id": 480583316, "v": 2}], "cloudTrackCount": 0, "shareCount": 4, "adType": 0}, "code": 200, "privileges": [{"toast": false, "dl": 0, "fee": 0, "subp": 1, "sp": 7, "preSell": false, "st": -100, "payed": 0, "flag": 0, "maxbr": 320000, "cs": false, "cp": 1, "fl": 0, "id": 507532080, "pl": 0}, {"toast": false, "dl": 0, "fee": 0, "subp": 1, "sp": 7, "preSell": false, "st": -100, "payed": 0, "flag": 0, "maxbr": 999000, "cs": false, "cp": 1, "fl": 0, "id": 507795601, "pl": 0}, {"toast": false, "dl": 0, "fee": 0, "subp": 1, "sp": 7, "preSell": false, "st": -100, "payed": 0, "flag": 0, "maxbr": 999000, "cs": false, "cp": 1, "fl": 320000, "id": 473940307, "pl": 0}, {"toast": false, "dl": 0, "fee": 0, "subp": 1, "sp": 7, "preSell": false, "st": -100, "payed": 0, "flag": 0, "maxbr": 320000, "cs": false, "cp": 1, "fl": 320000, "id": 491955309, "pl": 0}, {"toast": false, "dl": 0, "fee": 0, "subp": 1, "sp": 7, "preSell": false, "st": -100, "payed": 0, "flag": 0, "maxbr": 320000, "cs": false, "cp": 1, "fl": 0, "id": 476569154, "pl": 0}, {"toast": false, "dl": 0, "fee": 0, "subp": 1, "sp": 7, "preSell": false, "st": -100, "payed": 0, "flag": 0, "maxbr": 320000, "cs": false, "cp": 1, "fl": 0, "id": 470670960, "pl": 0}, {"toast": false, "dl": 0, "fee": 0, "subp": 1, "sp": 7, "preSell": false, "st": -100, "payed": 0, "flag": 0, "maxbr": 320000, "cs": false, "cp": 1, "fl": 0, "id": 490602605, "pl": 0}, {"toast": false, "dl": 0, "fee": 0, "subp": 1, "sp": 7, "preSell": false, "st": -100, "payed": 0, "flag": 0, "maxbr": 320000, "cs": false, "cp": 1, "fl": 0, "id": 498393830, "pl": 0}, {"toast": false, "dl": 0, "fee": 0, "subp": 1, "sp": 7, "preSell": false, "st": -100, "payed": 0, "flag": 0, "maxbr": 320000, "cs": false, "cp": 1, "fl": 320000, "id": 500686039, "pl": 0}, {"toast": false, "dl": 0, "fee": 0, "subp": 1, "sp": 7, "preSell": false, "st": -100, "payed": 0, "flag": 0, "maxbr": 999000, "cs": false, "cp": 1, "fl": 0, "id": 507795110, "pl": 0}]}