{"playlist": {"coverImgUrl": "http://p1.music.126.net/t4ORxlTYDUlZhEBOzfqf6g==/18998461416681667.jpg", "ordered": true, "creator": {"followed": false, "remarkName": null, "expertTags": null, "userId": 272662296, "authority": 0, "userType": 0, "experts": null, "gender": 1, "backgroundImgId": 109951163175735309, "city": 370900, "mutual": false, "avatarUrl": "http://p1.music.126.net/cra3ehZP8NnVypSfGxxXPw==/109951163175730947.jpg", "avatarImgIdStr": "109951163175730947", "detailDescription": "", "province": 370000, "description": "", "avatarImgId_str": "109951163175730947", "birthday": 992054843353, "nickname": "芋头地瓜烧", "vipType": 0, "avatarImgId": 109951163175730947, "defaultAvatar": false, "djStatus": 0, "accountStatus": 0, "backgroundImgIdStr": "109951163175735309", "backgroundUrl": "http://p1.music.126.net/KkZh68qvM7KTKii1TXXWSg==/109951163175735309.jpg", "signature": "这里是爱音乐的芋头，没错就这样。", "authStatus": 0}, "trackUpdateTime": 1521641464881, "coverImgId_str": "18998461416681667", "userId": 272662296, "updateTime": 1521641418113, "commentCount": 158, "newImported": false, "commentThreadId": "A_PL_0_2020493495", "subscribed": false, "privacy": 0, "id": 2020493495, "trackCount": 97, "specialType": 0, "status": 0, "description": "我们的口号是什么？？\n搞事！！！\n搞事！！！\n(ﾟ∀ﾟﾉ)ﾉ\n这当然是个搞事情歌单，同时有很多曲目也可以用来做视频啊小短片啊一类的。\n总结，复杂多样的搞事歌单。\n来源：日推，视频BGM等等等等（滑稽）\n\n搞这个歌单的目的嘛，\n还是希望大家能快乐啊~哎嘿嘿嘿嘿\n如果有推荐加入歌单的歌曲还可以私信我哦\n\n也许你是因为无聊把这个歌单翻了出来\n又或是因为某首歌网易爸爸把它推荐给你\n既然相遇，那边是缘分\n何不点个收藏呢？\n(≧ω≦)/\n", "subscribedCount": 18144, "tags": ["另类/独立", "流行", "快乐"], "trackNumberUpdateTime": 1521641418113, "tracks": [{"al": {"picUrl": "http://p1.music.126.net/claKS0BZfzaTqJAZcQjP5w==/3395291907804742.jpg", "pic": 3395291907804742, "id": 3094056, "tns": [], "name": "最新热歌慢摇93"}, "pop": 100.0, "cd": "", "s_id": 0, "ar": [{"alias": [], "id": 104700, "tns": [], "name": "Various Artists"}], "cp": 0, "id": 30148444, "rt": null, "fee": 0, "copyright": 2, "no": 1, "rtUrl": null, "mst": 9, "rtUrls": [], "ftype": 0, "h": null, "rurl": null, "publishTime": 1388505600004, "v": 208, "cf": "", "dt": 28656, "pst": 0, "a": null, "name": "happy tree friends 主题曲", "rtype": 0, "alia": [], "m": {"vd": 0.0, "fid": 0, "br": 128000, "size": 458756}, "l": {"vd": 0.374844, "fid": 0, "br": 96000, "size": 344966}, "st": 0, "djId": 0, "mv": 0, "t": 0, "crbt": null}, {"al": {"picUrl": "http://p1.music.126.net/GQ9JkLt6QBaAoLbJ8UOoCQ==/3406287023862462.jpg", "pic": 3406287023862462, "id": 3159840, "tns": [], "name": "热门华语266"}, "pop": 100.0, "cd": "", "s_id": 0, "ar": [{"alias": [], "id": 1081645, "tns": [], "name": "小胡仙儿"}], "cp": 0, "id": 32451809, "rt": null, "fee": 0, "copyright": 2, "no": 1, "rtUrl": null, "mst": 9, "rtUrls": [], "ftype": 0, "h": null, "rurl": null, "publishTime": 1388505600004, "v": 873, "cf": "", "dt": 191000, "pst": 0, "a": null, "name": "神经病之歌 - 二胡", "rtype": 0, "alia": [], "m": {"vd": -2.85, "fid": 0, "br": 128000, "size": 3062386}, "l": {"vd": -2.37, "fid": 0, "br": 96000, "size": 2297213}, "st": 0, "djId": 0, "mv": 0, "t": 0, "crbt": null}, {"al": {"picUrl": "http://p1.music.126.net/PeNkk0KyknsU9G_vUwMA2A==/848822976643265.jpg", "pic": 848822976643265, "id": 44667, "tns": [], "name": "らき☆すた DVD Vol.05 限定版 特典CD"}, "pop": 100.0, "cd": "1", "s_id": 0, "ar": [{"alias": [], "id": 14629, "tns": [], "name": "神前暁"}], "cp": 663018, "id": 462290, "rt": "", "fee": 0, "copyright": 2, "no": 4, "rtUrl": null, "mst": 9, "rtUrls": [], "ftype": 0, "h": {"vd": -1.93, "fid": 0, "br": 320000, "size": 1650692}, "rurl": null, "publishTime": 1193328000000, "v": 9, "cf": "", "dt": 40254, "pst": 0, "a": null, "name": "こなたのテーマ、インドバージョン", "rtype": 0, "alia": [], "m": {"vd": -1.44, "fid": 0, "br": 160000, "size": 845599}, "l": {"vd": -1.5, "fid": 0, "br": 96000, "size": 523144}, "st": 0, "djId": 0, "mv": 0, "t": 0, "crbt": null}, {"al": {"picUrl": "http://p1.music.126.net/UP01B43Qa7lVbJ9HrQcVBw==/5902178417933870.jpg", "pic": 5902178417933870, "id": 2685260, "tns": [], "name": "爸爸去哪儿 原声带"}, "pop": 95.0, "cd": "1", "s_id": 0, "ar": [{"alias": [], "id": 14629, "tns": [], "name": "神前暁"}], "cp": 0, "id": 28160324, "rt": "", "fee": 0, "copyright": 2, "no": 36, "rtUrl": null, "mst": 9, "rtUrls": [], "ftype": 0, "h": {"vd": 0.0, "fid": 0, "br": 320000, "size": 3862387}, "rurl": null, "publishTime": 1381593600007, "v": 666, "cf": "", "dt": 95817, "pst": 0, "a": null, "name": "これがオタクの生きる道", "rtype": 0, "alia": [], "m": {"vd": 0.0, "fid": 0, "br": 160000, "size": 1945000}, "l": {"vd": 0.0, "fid": 0, "br": 96000, "size": 1178045}, "st": 0, "djId": 0, "mv": 0, "t": 0, "crbt": null}, {"al": {"picUrl": "http://p1.music.126.net/u2sWlV-BqYyqDV7_zskZyw==/6634453163551437.jpg", "pic": 6634453163551437, "id": 3426233, "tns": [], "name": "The Party Troll"}, "pop": 100.0, "cd": "1", "s_id": 0, "ar": [{"alias": [], "id": 1058211, "tns": [], "name": "D1ofaquavibe"}], "cp": 0, "id": 38358820, "rt": null, "fee": 0, "copyright": 0, "no": 1, "rtUrl": null, "mst": 9, "rtUrls": [], "ftype": 0, "h": {"vd": -0.000265076, "fid": 0, "br": 320000, "size": 7559879}, "rurl": null, "publishTime": 1449554477094, "v": 5, "cf": "", "dt": 188784, "pst": 0, "a": null, "name": "The Party Troll", "rtype": 0, "alia": [], "m": {"vd": -0.000265076, "fid": 0, "br": 160000, "size": 3779962}, "l": {"vd": -0.000265076, "fid": 0, "br": 96000, "size": 2267995}, "st": 0, "djId": 0, "mv": 0, "t": 0, "crbt": null}, {"al": {"picUrl": "http://p1.music.126.net/2UGD8Wf8WSmulwu2EwrqeQ==/3391993372466843.jpg", "pic": 3391993372466843, "id": 3159844, "tns": [], "name": "最新热歌慢摇101"}, "pop": 100.0, "cd": "", "s_id": 0, "ar": [{"alias": [], "id": 0, "tns": [], "name": "银桑"}], "cp": 663018, "id": 32719453, "rt": null, "fee": 0, "copyright": 2, "no": 1, "rtUrl": null, "mst": 9, "rtUrls": [], "ftype": 0, "h": null, "rurl": null, "publishTime": 1420041600004, "v": 586, "cf": "", "dt": 29000, "pst": 0, "a": null, "name": "哆啦A梦", "rtype": 0, "alia": [], "m": {"vd": 0.821203, "fid": 0, "br": 127000, "size": 466023}, "l": {"vd": 1.25798, "fid": 0, "br": 96000, "size": 350189}, "st": 0, "djId": 0, "mv": 0, "t": 0, "crbt": null}, {"al": {"picUrl": "http://p1.music.126.net/5durIn0WQTKS9HSF_pSs8A==/3261151489674621.jpg", "pic": 3261151489674621, "id": 3094379, "tns": [], "name": "热门华语259"}, "pop": 100.0, "cd": "1", "s_id": 0, "ar": [{"alias": [], "id": 900347, "tns": [], "name": "小旭音乐"}], "cp": 0, "id": 30260225, "rt": null, "fee": 0, "copyright": 2, "no": 1, "rtUrl": null, "mst": 9, "rtUrls": [], "ftype": 0, "h": null, "rurl": null, "publishTime": 1388505600004, "v": 720, "cf": "", "dt": 106527, "pst": 0, "a": null, "name": "欢乐斗地主背景音乐", "rtype": 0, "alia": [], "m": {"vd": -0.000265076, "fid": 0, "br": 128000, "size": 1705919}, "l": {"vd": -0.000265076, "fid": 0, "br": 96000, "size": 1280020}, "st": 0, "djId": 0, "mv": 0, "t": 0, "crbt": null}, {"al": {"picUrl": "http://p1.music.126.net/3MrR9xSZt3Hal_2AIW2dXA==/1349100767337953.jpg", "pic": 1349100767337953, "id": 2685649, "tns": [], "name": "热门网络歌曲合集"}, "pop": 100.0, "cd": "", "s_id": 0, "ar": [{"alias": [], "id": 0, "tns": [], "name": "량현량하"}], "cp": 0, "id": 27965452, "rt": "", "fee": 0, "copyright": 2, "no": 1, "rtUrl": null, "mst": 9, "rtUrls": [], "ftype": 0, "h": null, "rurl": null, "publishTime": 1356969600004, "v": 673, "cf": "", "dt": 246360, "pst": 0, "a": null, "name": "학교를 안갔어!", "tns": ["What Is Dancing", "没有去学校"], "rtype": 0, "alia": ["What Is Dancing", "没有去学校"], "m": {"vd": -1.9, "fid": 0, "br": 128000, "size": 3976026}, "l": {"vd": -1.45, "fid": 0, "br": 96000, "size": 2990792}, "st": 0, "djId": 0, "mv": 0, "t": 0, "crbt": null}, {"al": {"picUrl": "http://p1.music.126.net/CU9t31gRDyubIr4wBXqCdA==/7775746232680070.jpg", "pic": 7775746232680070, "id": 3196091, "tns": [], "name": "Trap Shit V22"}, "pop": 100.0, "cd": "1", "s_id": 0, "ar": [{"alias": [], "id": 806147, "tns": [], "name": "ƱZ"}], "cp": 0, "id": 33255655, "rt": null, "fee": 0, "copyright": 0, "no": 1, "rtUrl": null, "mst": 9, "rtUrls": [], "ftype": 0, "h": {"vd": -1.35, "fid": 0, "br": 320000, "size": 8864052}, "rurl": null, "publishTime": 1426348800007, "v": 5, "cf": "", "dt": 221000, "pst": 0, "a": null, "name": "Trap Shit V22", "rtype": 0, "alia": [], "m": {"vd": -0.92, "fid": 0, "br": 160000, "size": 4432118}, "l": {"vd": -0.97, "fid": 0, "br": 96000, "size": 2659344}, "st": 0, "djId": 0, "mv": 0, "t": 0, "crbt": null}, {"al": {"picUrl": "http://p1.music.126.net/iR_u6YNOzfQ2g1FL_A6Msw==/5836207720467261.jpg", "pic": 5836207720467261, "id": 2896110, "tns": [], "name": "Toca Toca (The Remixes)"}, "pop": 100.0, "cd": "1", "s_id": 0, "ar": [{"alias": [], "id": 92933, "tns": [], "name": "Fly Project"}], "cp": 405025, "id": 28796621, "rt": null, "fee": 8, "copyright": 2, "no": 5, "rtUrl": null, "mst": 9, "rtUrls": [], "ftype": 0, "h": {"vd": -3.57, "fid": 0, "br": 320000, "size": 6621563}, "rurl": null, "publishTime": 1392220800007, "v": 5, "cf": "", "dt": 165459, "pst": 0, "a": null, "name": "Toca Toca (Radio Edit)", "rtype": 0, "alia": [], "m": {"vd": -3.18, "fid": 0, "br": 160000, "size": 3311327}, "l": {"vd": -3.2, "fid": 0, "br": 96000, "size": 1987233}, "st": 0, "djId": 0, "mv": 0, "t": 0, "crbt": null}], "highQuality": false, "subscribers": [], "playCount": 419876, "coverImgId": 18998461416681667, "createTime": 1513603897090, "name": "你所耳熟能详的搞事情歌单【魔性循环】", "trackIds": [{"id": 30148444, "v": 208}, {"id": 32451809, "v": 873}, {"id": 462290, "v": 9}, {"id": 28160324, "v": 666}, {"id": 38358820, "v": 5}, {"id": 32719453, "v": 586}, {"id": 30260225, "v": 720}, {"id": 27965452, "v": 673}, {"id": 33255655, "v": 5}, {"id": 28796621, "v": 5}, {"id": 21940256, "v": 10}, {"id": 33392461, "v": 10}, {"id": 22660279, "v": 4}, {"id": 423227267, "v": 4}, {"id": 33111975, "v": 233}, {"id": 518088613, "v": 8}, {"id": 3949444, "v": 16}, {"id": 26608473, "v": 461}, {"id": 26608481, "v": 461}, {"id": 26667946, "v": 4}, {"id": 1992744, "v": 14}, {"id": 33035611, "v": 7}, {"id": 535032, "v": 8}, {"id": 5398837, "v": 796}, {"id": 26548584, "v": 165}, {"id": 5143941, "v": 146}, {"id": 25657233, "v": 90}, {"id": 432821633, "v": 27}, {"id": 4971469, "v": 462}, {"id": 424262521, "v": 76}, {"id": 29822196, "v": 214}, {"id": 27534134, "v": 669}, {"id": 29043343, "v": 465}, {"id": 811820, "v": 6}, {"id": 28762209, "v": 4}, {"id": 29789260, "v": 3}, {"id": 4960496, "v": 5}, {"id": 28625030, "v": 231}, {"id": 31246600, "v": 5}, {"id": 223339, "v": 18}, {"id": 758330, "v": 5}, {"id": 4880102, "v": 468}, {"id": 29129030, "v": 9}, {"id": 22457277, "v": 138}, {"id": 27518583, "v": 2}, {"id": 1489019, "v": 15}, {"id": 4964085, "v": 15}, {"id": 784511, "v": 6}, {"id": 34376545, "v": 37}, {"id": 5413713, "v": 456}, {"id": 18137221, "v": 18}, {"id": 28785339, "v": 8}, {"id": 28191149, "v": 392}, {"id": 403711640, "v": 1}, {"id": 26214251, "v": 7}, {"id": 5050653, "v": 31}, {"id": 1992741, "v": 13}, {"id": 2740360, "v": 4}, {"id": 27772712, "v": 146}, {"id": 17241116, "v": 14}, {"id": 28720158, "v": 6}, {"id": 1062642, "v": 11}, {"id": 2866921, "v": 6}, {"id": 33004351, "v": 7}, {"id": 399410728, "v": 6}, {"id": 5099470, "v": 141}, {"id": 1371159, "v": 3}, {"id": 401723106, "v": 13}, {"id": 29775322, "v": 149}, {"id": 1322313, "v": 4}, {"id": 457623758, "v": 8}, {"id": 344719, "v": 11}, {"id": 16823382, "v": 15}, {"id": 5259345, "v": 669}, {"id": 27552544, "v": 10}, {"id": 27552548, "v": 13}, {"id": 5184412, "v": 138}, {"id": 395418, "v": 10}, {"id": 395588, "v": 8}, {"id": 395434, "v": 5}, {"id": 395304, "v": 3}, {"id": 30431278, "v": 693}, {"id": 283763, "v": 7}, {"id": 431096392, "v": 4}, {"id": 5263408, "v": 669}, {"id": 92569, "v": 6}, {"id": 31341931, "v": 2}, {"id": 128669, "v": 7}, {"id": 758649, "v": 5}, {"id": 28188299, "v": 9}, {"id": 74576, "v": 3}, {"id": 29046312, "v": 29}, {"id": 5295089, "v": 76}, {"id": 31421220, "v": 89}, {"id": 5051245, "v": 57}, {"id": 19067286, "v": 8}, {"id": 29816860, "v": 12}], "cloudTrackCount": 0, "shareCount": 200, "adType": 0}, "code": 200, "privileges": [{"toast": false, "dl": 0, "fee": 0, "subp": 1, "sp": 7, "preSell": false, "st": -100, "payed": 0, "flag": 0, "maxbr": 96000, "cs": false, "cp": 1, "fl": 320000, "id": 30148444, "pl": 0}, {"toast": false, "dl": 0, "fee": 0, "subp": 1, "sp": 7, "preSell": false, "st": -100, "payed": 0, "flag": 0, "maxbr": 128000, "cs": false, "cp": 1, "fl": 320000, "id": 32451809, "pl": 0}, {"toast": false, "dl": 0, "fee": 0, "subp": 1, "sp": 7, "preSell": false, "st": -100, "payed": 0, "flag": 0, "maxbr": 320000, "cs": false, "cp": 1, "fl": 320000, "id": 462290, "pl": 0}, {"toast": false, "dl": 0, "fee": 0, "subp": 1, "sp": 7, "preSell": false, "st": -100, "payed": 0, "flag": 0, "maxbr": 320000, "cs": false, "cp": 1, "fl": 320000, "id": 28160324, "pl": 0}, {"toast": false, "dl": 0, "fee": 0, "subp": 1, "sp": 7, "preSell": false, "st": -100, "payed": 0, "flag": 0, "maxbr": 320000, "cs": false, "cp": 1, "fl": 320000, "id": 38358820, "pl": 0}, {"toast": false, "dl": 0, "fee": 0, "subp": 1, "sp": 7, "preSell": false, "st": -100, "payed": 0, "flag": 0, "maxbr": 96000, "cs": false, "cp": 1, "fl": 320000, "id": 32719453, "pl": 0}, {"toast": false, "dl": 0, "fee": 0, "subp": 1, "sp": 7, "preSell": false, "st": -100, "payed": 0, "flag": 0, "maxbr": 128000, "cs": false, "cp": 1, "fl": 320000, "id": 30260225, "pl": 0}, {"toast": false, "dl": 0, "fee": 0, "subp": 1, "sp": 7, "preSell": false, "st": -100, "payed": 0, "flag": 0, "maxbr": 128000, "cs": false, "cp": 1, "fl": 320000, "id": 27965452, "pl": 0}, {"toast": false, "dl": 0, "fee": 0, "subp": 1, "sp": 7, "preSell": false, "st": -100, "payed": 0, "flag": 0, "maxbr": 320000, "cs": false, "cp": 1, "fl": 320000, "id": 33255655, "pl": 0}, {"toast": false, "dl": 0, "fee": 0, "subp": 1, "sp": 7, "preSell": false, "st": -100, "payed": 0, "flag": 0, "maxbr": 320000, "cs": false, "cp": 1, "fl": 0, "id": 28796621, "pl": 0}]}